aolney_jupyterlab_blockly_python_extension/__init__.py
aolney_jupyterlab_blockly_python_extension/_version.py
aolney_jupyterlab_blockly_python_extension-0.2.2.data/data/share/jupyter/labextensions/@aolney/jupyterlab-blockly-python-extension/package.json
aolney_jupyterlab_blockly_python_extension-0.2.2.data/data/share/jupyter/labextensions/@aolney/jupyterlab-blockly-python-extension/static/203.b299ad15bde3bf522b32.js
aolney_jupyterlab_blockly_python_extension-0.2.2.data/data/share/jupyter/labextensions/@aolney/jupyterlab-blockly-python-extension/static/203.b299ad15bde3bf522b32.js.LICENSE.txt
aolney_jupyterlab_blockly_python_extension-0.2.2.data/data/share/jupyter/labextensions/@aolney/jupyterlab-blockly-python-extension/static/369.b762c689b438a7ed8ada.js
aolney_jupyterlab_blockly_python_extension-0.2.2.data/data/share/jupyter/labextensions/@aolney/jupyterlab-blockly-python-extension/static/369.b762c689b438a7ed8ada.js.LICENSE.txt
aolney_jupyterlab_blockly_python_extension-0.2.2.data/data/share/jupyter/labextensions/@aolney/jupyterlab-blockly-python-extension/static/396.c16b777218a776ceb1b1.js
aolney_jupyterlab_blockly_python_extension-0.2.2.data/data/share/jupyter/labextensions/@aolney/jupyterlab-blockly-python-extension/static/396.c16b777218a776ceb1b1.js.LICENSE.txt
aolney_jupyterlab_blockly_python_extension-0.2.2.data/data/share/jupyter/labextensions/@aolney/jupyterlab-blockly-python-extension/static/477.95aeb3e5f3e044d6487a.js
aolney_jupyterlab_blockly_python_extension-0.2.2.data/data/share/jupyter/labextensions/@aolney/jupyterlab-blockly-python-extension/static/603.17c6fa7216ebca44db94.js
aolney_jupyterlab_blockly_python_extension-0.2.2.data/data/share/jupyter/labextensions/@aolney/jupyterlab-blockly-python-extension/static/603.17c6fa7216ebca44db94.js.LICENSE.txt
aolney_jupyterlab_blockly_python_extension-0.2.2.data/data/share/jupyter/labextensions/@aolney/jupyterlab-blockly-python-extension/static/728.0ce0341aafcfe5be1ea3.js
aolney_jupyterlab_blockly_python_extension-0.2.2.dist-info/METADATA
aolney_jupyterlab_blockly_python_extension-0.2.2.dist-info/WHEEL
aolney_jupyterlab_blockly_python_extension-0.2.2.dist-info/licenses/LICENSE
aolney_jupyterlab_blockly_python_extension-0.2.2.dist-info/RECORD
