Metadata-Version: 2.4
Name: aolney_jupyterlab_blockly_python_extension
Version: 0.2.2
Dynamic: Keywords
Summary: A JupyterLab extension that creates a Blockly palette for Python.
Project-URL: Homepage, https://github.com/aolney/jupyterlab-blockly-python-extension
Project-URL: Bug Tracker, https://github.com/aolney/jupyterlab-blockly-python-extension/issues
Project-URL: Repository, https://github.com/aolney/jupyterlab-blockly-python-extension.git
Author-email: "Andrew M. Olney" <aolney@memphis.edu>
License:                                  Apache License
License-File: LICENSE
Classifier: Framework :: Jupyter
Classifier: Framework :: Jupyter :: JupyterLab
Classifier: Framework :: Jupyter :: JupyterLab :: 4
Classifier: Framework :: Jupyter :: JupyterLab :: Extensions
Classifier: Framework :: Jupyter :: JupyterLab :: Extensions :: Prebuilt
Classifier: License :: OSI Approved :: BSD License
Classifier: Programming Language :: Python
Classifier: Programming Language :: Python :: 3
Classifier: Programming Language :: Python :: 3.8
Classifier: Programming Language :: Python :: 3.9
Classifier: Programming Language :: Python :: 3.10
Classifier: Programming Language :: Python :: 3.11
Classifier: Programming Language :: Python :: 3.12
Requires-Python: >=3.8
